{"fileStats":[{"fileName":"OPS/titlepage.xhtml","charCount":78,"wordCount":12},{"fileName":"OPS/cover.xhtml","charCount":14,"wordCount":2},{"fileName":"OPS/copyright-page.xhtml","charCount":612,"wordCount":79},{"fileName":"OPS/biography.xhtml","charCount":1570,"wordCount":201},{"fileName":"OPS/titlepage.xhtml","charCount":78,"wordCount":12},{"fileName":"OPS/preface.xhtml","charCount":14126,"wordCount":1882},{"fileName":"OPS/chapter1.xhtml","charCount":5569,"wordCount":777},{"fileName":"OPS/chapter2.xhtml","charCount":6501,"wordCount":853},{"fileName":"OPS/chapter3.xhtml","charCount":6280,"wordCount":858},{"fileName":"OPS/chapter4.xhtml","charCount":11937,"wordCount":1645},{"fileName":"OPS/chapter5_split_000.xhtml","charCount":24283,"wordCount":3213},{"fileName":"OPS/chapter5_split_001.xhtml","charCount":15799,"wordCount":2084},{"fileName":"OPS/chapter5_split_002.xhtml","charCount":25018,"wordCount":3346},{"fileName":"OPS/chapter5_split_003.xhtml","charCount":24412,"wordCount":3303},{"fileName":"OPS/chapter5_split_004.xhtml","charCount":18198,"wordCount":2424},{"fileName":"OPS/chapter5_split_005.xhtml","charCount":21658,"wordCount":2930},{"fileName":"OPS/chapter5_split_006.xhtml","charCount":35612,"wordCount":4760},{"fileName":"OPS/chapter6.xhtml","charCount":25181,"wordCount":3432},{"fileName":"OPS/chapter7.xhtml","charCount":11765,"wordCount":1543},{"fileName":"OPS/chapter8.xhtml","charCount":13056,"wordCount":1754},{"fileName":"OPS/chapter9.xhtml","charCount":23123,"wordCount":3084},{"fileName":"OPS/chapter10_split_000.xhtml","charCount":30220,"wordCount":4008},{"fileName":"OPS/chapter10_split_001.xhtml","charCount":28722,"wordCount":3833},{"fileName":"OPS/chapter11.xhtml","charCount":22486,"wordCount":2953},{"fileName":"OPS/chapter12.xhtml","charCount":15943,"wordCount":2131},{"fileName":"OPS/chapter13.xhtml","charCount":27839,"wordCount":3740},{"fileName":"OPS/chapter14.xhtml","charCount":5419,"wordCount":717},{"fileName":"OPS/chapter15.xhtml","charCount":17325,"wordCount":2331},{"fileName":"OPS/chapter16.xhtml","charCount":9162,"wordCount":1258},{"fileName":"OPS/chapter17.xhtml","charCount":33654,"wordCount":4509},{"fileName":"OPS/chapter18.xhtml","charCount":15453,"wordCount":2120},{"fileName":"OPS/chapter19_split_000.xhtml","charCount":39349,"wordCount":5390},{"fileName":"OPS/chapter19_split_001.xhtml","charCount":29413,"wordCount":3997},{"fileName":"OPS/chapter20.xhtml","charCount":9789,"wordCount":1334},{"fileName":"OPS/chapter21.xhtml","charCount":9531,"wordCount":1260},{"fileName":"OPS/chapter22.xhtml","charCount":10812,"wordCount":1430},{"fileName":"OPS/chapter23.xhtml","charCount":12498,"wordCount":1695},{"fileName":"OPS/chapter24.xhtml","charCount":32847,"wordCount":4471},{"fileName":"OPS/chapter25.xhtml","charCount":5268,"wordCount":707},{"fileName":"OPS/chapter26.xhtml","charCount":16165,"wordCount":2186},{"fileName":"OPS/chapter27.xhtml","charCount":14001,"wordCount":1849},{"fileName":"OPS/chapter28.xhtml","charCount":6361,"wordCount":859},{"fileName":"OPS/chapter29.xhtml","charCount":7719,"wordCount":1033},{"fileName":"OPS/chapter30.xhtml","charCount":45395,"wordCount":6044},{"fileName":"OPS/bibliography.xhtml","charCount":2405,"wordCount":340},{"fileName":"OPS/index_split_000.xhtml","charCount":6676,"wordCount":1744},{"fileName":"OPS/index_split_001.xhtml","charCount":5805,"wordCount":1317},{"fileName":"OPS/index_split_002.xhtml","charCount":6118,"wordCount":1504},{"fileName":"OPS/index_split_003.xhtml","charCount":6557,"wordCount":1691},{"fileName":"OPS/index_split_004.xhtml","charCount":5964,"wordCount":1435},{"fileName":"OPS/index_split_005.xhtml","charCount":5650,"wordCount":1335},{"fileName":"OPS/index_split_006.xhtml","charCount":5894,"wordCount":1436},{"fileName":"OPS/index_split_007.xhtml","charCount":5949,"wordCount":1460}],"totalCharacterCount":781259,"totalWordCount":110311}