{"fileStats":[{"fileName":"titlepage.xhtml","charCount":0,"wordCount":0},{"fileName":"OEBPS/on_kapak.xhtml","charCount":52,"wordCount":8},{"fileName":"OEBPS/1.xhtml","charCount":108,"wordCount":14},{"fileName":"OEBPS/1-1.xhtml","charCount":816,"wordCount":111},{"fileName":"OEBPS/1-2.xhtml","charCount":3819,"wordCount":519},{"fileName":"OEBPS/1-3.xhtml","charCount":300,"wordCount":49},{"fileName":"OEBPS/1-4.xhtml","charCount":219,"wordCount":36},{"fileName":"OEBPS/1-5.xhtml","charCount":383,"wordCount":56},{"fileName":"OEBPS/1-6.xhtml","charCount":492,"wordCount":80},{"fileName":"OEBPS/1-7.xhtml","charCount":814,"wordCount":113},{"fileName":"OEBPS/1-8.xhtml","charCount":1208,"wordCount":175},{"fileName":"OEBPS/1-9.xhtml","charCount":518,"wordCount":71},{"fileName":"OEBPS/1-10.xhtml","charCount":459,"wordCount":64},{"fileName":"OEBPS/1-11.xhtml","charCount":688,"wordCount":96},{"fileName":"OEBPS/1-12.xhtml","charCount":2838,"wordCount":410},{"fileName":"OEBPS/1-13.xhtml","charCount":1410,"wordCount":208},{"fileName":"OEBPS/1-14.xhtml","charCount":347,"wordCount":42},{"fileName":"OEBPS/1-15.xhtml","charCount":372,"wordCount":50},{"fileName":"OEBPS/1-16.xhtml","charCount":1600,"wordCount":249},{"fileName":"OEBPS/1-17.xhtml","charCount":311,"wordCount":45},{"fileName":"OEBPS/1-18.xhtml","charCount":3143,"wordCount":461},{"fileName":"OEBPS/1-19.xhtml","charCount":829,"wordCount":108},{"fileName":"OEBPS/1-20.xhtml","charCount":1956,"wordCount":252},{"fileName":"OEBPS/1-21.xhtml","charCount":255,"wordCount":40},{"fileName":"OEBPS/1-22.xhtml","charCount":144,"wordCount":23},{"fileName":"OEBPS/1-23.xhtml","charCount":505,"wordCount":69},{"fileName":"OEBPS/1-24.xhtml","charCount":383,"wordCount":52},{"fileName":"OEBPS/1-25.xhtml","charCount":780,"wordCount":89},{"fileName":"OEBPS/1-26.xhtml","charCount":1004,"wordCount":164},{"fileName":"OEBPS/1-27.xhtml","charCount":456,"wordCount":66},{"fileName":"OEBPS/1-28.xhtml","charCount":507,"wordCount":74},{"fileName":"OEBPS/1-29.xhtml","charCount":1201,"wordCount":169},{"fileName":"OEBPS/1-30.xhtml","charCount":198,"wordCount":29},{"fileName":"OEBPS/1-31.xhtml","charCount":857,"wordCount":120},{"fileName":"OEBPS/1-32.xhtml","charCount":440,"wordCount":69},{"fileName":"OEBPS/1-33.xhtml","charCount":237,"wordCount":33},{"fileName":"OEBPS/1-34.xhtml","charCount":248,"wordCount":38},{"fileName":"OEBPS/1-35.xhtml","charCount":315,"wordCount":45},{"fileName":"OEBPS/1-36.xhtml","charCount":361,"wordCount":53},{"fileName":"OEBPS/1-37.xhtml","charCount":568,"wordCount":88},{"fileName":"OEBPS/1-38.xhtml","charCount":214,"wordCount":28},{"fileName":"OEBPS/1-39.xhtml","charCount":183,"wordCount":29},{"fileName":"OEBPS/1-40.xhtml","charCount":182,"wordCount":28},{"fileName":"OEBPS/1-41.xhtml","charCount":260,"wordCount":40},{"fileName":"OEBPS/1-42.xhtml","charCount":338,"wordCount":50},{"fileName":"OEBPS/1-43.xhtml","charCount":3447,"wordCount":480},{"fileName":"OEBPS/1-44.xhtml","charCount":436,"wordCount":60},{"fileName":"OEBPS/1-45.xhtml","charCount":187,"wordCount":28},{"fileName":"OEBPS/1-46.xhtml","charCount":194,"wordCount":25},{"fileName":"OEBPS/1-47.xhtml","charCount":205,"wordCount":29},{"fileName":"OEBPS/1-48.xhtml","charCount":282,"wordCount":35},{"fileName":"OEBPS/1-49.xhtml","charCount":418,"wordCount":55},{"fileName":"OEBPS/1-50.xhtml","charCount":346,"wordCount":48},{"fileName":"OEBPS/1-51.xhtml","charCount":272,"wordCount":41},{"fileName":"OEBPS/1-52.xhtml","charCount":563,"wordCount":78},{"fileName":"OEBPS/1-53.xhtml","charCount":582,"wordCount":73},{"fileName":"OEBPS/1-54.xhtml","charCount":2293,"wordCount":323},{"fileName":"OEBPS/1-55.xhtml","charCount":1674,"wordCount":219},{"fileName":"OEBPS/1-56.xhtml","charCount":907,"wordCount":104},{"fileName":"OEBPS/1-57.xhtml","charCount":305,"wordCount":45},{"fileName":"OEBPS/1-58.xhtml","charCount":1017,"wordCount":141},{"fileName":"OEBPS/1-59.xhtml","charCount":339,"wordCount":46},{"fileName":"OEBPS/1-60.xhtml","charCount":654,"wordCount":97},{"fileName":"OEBPS/1-61.xhtml","charCount":587,"wordCount":83},{"fileName":"OEBPS/1-62.xhtml","charCount":234,"wordCount":36},{"fileName":"OEBPS/1-63.xhtml","charCount":585,"wordCount":90},{"fileName":"OEBPS/1-64.xhtml","charCount":744,"wordCount":86},{"fileName":"OEBPS/1-65.xhtml","charCount":549,"wordCount":83},{"fileName":"OEBPS/1-66.xhtml","charCount":447,"wordCount":61},{"fileName":"OEBPS/1-67.xhtml","charCount":120,"wordCount":15},{"fileName":"OEBPS/1-68.xhtml","charCount":894,"wordCount":118},{"fileName":"OEBPS/1-69.xhtml","charCount":402,"wordCount":58},{"fileName":"OEBPS/1-70.xhtml","charCount":251,"wordCount":42},{"fileName":"OEBPS/1-71.xhtml","charCount":259,"wordCount":34},{"fileName":"OEBPS/1-72.xhtml","charCount":359,"wordCount":62},{"fileName":"OEBPS/1-73.xhtml","charCount":430,"wordCount":72},{"fileName":"OEBPS/1-74.xhtml","charCount":429,"wordCount":65},{"fileName":"OEBPS/1-75.xhtml","charCount":385,"wordCount":60},{"fileName":"OEBPS/1-76.xhtml","charCount":467,"wordCount":63},{"fileName":"OEBPS/1-77.xhtml","charCount":292,"wordCount":48},{"fileName":"OEBPS/1-78.xhtml","charCount":371,"wordCount":57},{"fileName":"OEBPS/1-79.xhtml","charCount":348,"wordCount":52},{"fileName":"OEBPS/1-80.xhtml","charCount":379,"wordCount":52},{"fileName":"OEBPS/1-81.xhtml","charCount":390,"wordCount":62},{"fileName":"OEBPS/1-82.xhtml","charCount":647,"wordCount":98},{"fileName":"OEBPS/1-83.xhtml","charCount":387,"wordCount":57},{"fileName":"OEBPS/1-84.xhtml","charCount":449,"wordCount":63},{"fileName":"OEBPS/1-85.xhtml","charCount":331,"wordCount":54},{"fileName":"OEBPS/1-86.xhtml","charCount":203,"wordCount":34},{"fileName":"OEBPS/1-87.xhtml","charCount":243,"wordCount":36},{"fileName":"OEBPS/1-88.xhtml","charCount":475,"wordCount":82},{"fileName":"OEBPS/1-89.xhtml","charCount":505,"wordCount":72},{"fileName":"OEBPS/1-90.xhtml","charCount":483,"wordCount":72},{"fileName":"OEBPS/1-91.xhtml","charCount":162,"wordCount":24},{"fileName":"OEBPS/1-92.xhtml","charCount":351,"wordCount":53},{"fileName":"OEBPS/1-93.xhtml","charCount":435,"wordCount":65},{"fileName":"OEBPS/1-94.xhtml","charCount":506,"wordCount":77},{"fileName":"OEBPS/1-95.xhtml","charCount":925,"wordCount":149},{"fileName":"OEBPS/1-96.xhtml","charCount":1027,"wordCount":150},{"fileName":"OEBPS/1-97.xhtml","charCount":537,"wordCount":81},{"fileName":"OEBPS/1-98.xhtml","charCount":151,"wordCount":27},{"fileName":"OEBPS/1-99.xhtml","charCount":406,"wordCount":68},{"fileName":"OEBPS/1-100.xhtml","charCount":393,"wordCount":58},{"fileName":"OEBPS/1-101.xhtml","charCount":465,"wordCount":75},{"fileName":"OEBPS/1-102.xhtml","charCount":278,"wordCount":42},{"fileName":"OEBPS/1-103.xhtml","charCount":3842,"wordCount":871},{"fileName":"OEBPS/1-104.xhtml","charCount":2491,"wordCount":339},{"fileName":"OEBPS/1-105.xhtml","charCount":197,"wordCount":26}],"totalCharacterCount":71250,"totalWordCount":10512}